dredd_core/__init__.py
dredd_core/engine.py
dredd_core-0.1.0.dist-info/licenses/LICENSE
dredd_core-0.1.0.dist-info/METADATA
dredd_core-0.1.0.dist-info/WHEEL
dredd_core-0.1.0.dist-info/top_level.txt
dredd_core-0.1.0.dist-info/RECORD
