Metadata-Version: 2.4
Name: dredd-core
Version: 0.1.0
Summary: DA-BFT Tribunal Engine - Divergent Arbiter Byzantine Fault Tolerance for multi-model AI consensus
Author-email: Jonathan David Harrison Miller <owner.founder@noteworthyendeavors.com>
License: # Polyform Small Business License 1.0.0 (Modified)
Project-URL: Homepage, https://github.com/noteworthyendeavors/dredd-core
Keywords: bft,consensus,ai,llm,arbitration,multi-model
Classifier: Development Status :: 3 - Alpha
Classifier: Intended Audience :: Developers
Classifier: Programming Language :: Python :: 3
Classifier: Programming Language :: Python :: 3.9
Classifier: Programming Language :: Python :: 3.10
Classifier: Programming Language :: Python :: 3.11
Classifier: Programming Language :: Python :: 3.12
Requires-Python: >=3.9
License-File: LICENSE
Requires-Dist: groq
Requires-Dist: anthropic
Requires-Dist: python-dotenv
Dynamic: license-file
